<?xml version="1.0" ?>
<PyBrain>
	<Network class="pybrain.structure.networks.feedforward.FeedForwardNetwork" name="FeedForwardNetwork-53">
		<name val="'FeedForwardNetwork-53'"/>
		<Modules>
			<LinearLayer class="pybrain.structure.modules.linearlayer.LinearLayer" inmodule="True" name="in">
				<name val="'in'"/>
				<dim val="33"/>
			</LinearLayer>
			<LinearLayer class="pybrain.structure.modules.linearlayer.LinearLayer" name="out" outmodule="True">
				<name val="'out'"/>
				<dim val="2"/>
			</LinearLayer>
			<BiasUnit class="pybrain.structure.modules.biasunit.BiasUnit" name="bias">
				<name val="'bias'"/>
			</BiasUnit>
			<SigmoidLayer class="pybrain.structure.modules.sigmoidlayer.SigmoidLayer" name="hidden0">
				<name val="'hidden0'"/>
				<dim val="50"/>
			</SigmoidLayer>
		</Modules>
		<Connections>
			<FullConnection class="pybrain.structure.connections.full.FullConnection" name="FullConnection-50">
				<inmod val="bias"/>
				<outmod val="out"/>
				<Parameters>[0.96199005983420516, 0.41907227215283416]</Parameters>
			</FullConnection>
			<FullConnection class="pybrain.structure.connections.full.FullConnection" name="FullConnection-51">
				<inmod val="bias"/>
				<outmod val="hidden0"/>
				<Parameters>[0.24885558783053685, 1.1400917628171441, 2.1757570531331032, -0.80465233085525822, 0.96623395512721655, 1.8858662174569714, -0.17852664167725765, -0.44895918233827264, -0.15990331700543201, -0.86052292431951505, 2.2314225356081567, 1.31227555650579, 1.23754335193155, 0.28717882953275631, -0.48293125028613909, 2.4875367230759156, -0.077216214932275692, 0.26954792843844572, -1.0422026817887848, 0.49532411912131086, -0.13784173269787511, -0.18611496861765117, -0.63272911403835141, -0.33164321637704663, -0.40687736814257813, -0.68821571092965594, -1.2149002455415721, -0.056281011451201561, -0.073417117394344672, -0.87973507052713362, -0.23925944089411477, 0.75760683039612686, -0.41310280988487963, 0.36605209330098104, 0.011399048578070493, 0.61088273103447155, -0.1686510524991475, -0.00046195486844887199, -0.40281136733726058, -0.1911297913458268, -1.0992329995587464, -0.33566882529909159, 0.65416793230485848, -1.0179094842961998, -0.50274708594003725, 0.025817391294039795, -0.77543861928564017, -0.5491133961437743, -0.35515098633986136, -0.83181135352478686]</Parameters>
			</FullConnection>
			<FullConnection class="pybrain.structure.connections.full.FullConnection" name="FullConnection-49">
				<inmod val="in"/>
				<outmod val="hidden0"/>
				<Parameters>[-2.8336280319634937, 1.4351012260553022, -0.40094904439946988, -0.47631108259807198, -0.79502058500227857, -0.12784850784926377, -0.77768352242680328, -0.19073080250934876, 0.18251178932986672, 0.0063245974732608571, -1.2362014647762825, 1.4386961384998165, -0.16563675816277146, -0.30714500117693982, 0.04561071606683343, -0.65705126691688975, -0.36202408555053378, -1.0063023577351315, -0.49468746175888878, 0.98532591456133789, -0.041952769853129873, -0.16704631501339895, -1.1555563578418235, 0.0436982444546824, -1.3376246034963857, 0.41677591365258881, 0.97728707100477963, 1.118559944770815, -0.11776290805328921, 0.10052565253285328, -0.78699897503161498, 0.94070701125809353, 0.19133050864743895, -0.4592415689472939, 2.278589298905084, 0.65925157043192928, -0.19671185428007373, 0.68462092027198806, 0.10208602394468891, -0.79884661766617204, -2.0560354019678226, -1.324474921044021, -2.2009299718916608, 1.7519362728751313, -0.20199329624647058, 0.42949895953831879, -2.3056402385808137, -0.59315826915773295, 1.5182779369712254, -0.98855448597384887, -0.79057685789220067, -0.77906946688420042, -1.1498708373320714, 1.5982969805483576, 0.57379297006785557, -0.0054211218961679481, 1.2660439860664949, -1.4654829261229827, 0.048860563192091949, -1.5502580260932597, 0.2934901694243125, -0.15617333591717972, -0.17368822696447442, 0.97487673665123065, 0.061170740977746066, 0.10001178612312027, 0.083346485176289384, -0.8470454064074302, 0.32433587424938737, 2.7639307248671741, -0.3726086252200701, -1.3251634643426504, 1.081456162328633, -1.5487670282925572, 0.68915652177999087, 0.79240173874665509, 0.49126817722978294, 0.84584753728870821, -2.0258368332026282, -0.38751979827118482, 0.6384909795416529, 0.15144002187099023, 0.4545928170592719, -0.72037924539448595, 0.72343215227841462, -0.35034762568094452, 0.13919868097112117, 1.9706855382558199, 0.7548012062779238, 0.78877112663929339, -0.31802178436719658, 1.4864028436657188, -1.0142808383834285, 0.66055543608649192, 0.55177922107213484, -1.668966379397663, 0.49982479524685219, 0.94768070845522967, -2.049690683575816, 0.28132783443486875, -0.11983471699543523, 0.87648588389800119, 3.416734622396139, -0.63468194366399999, 0.52963531361991201, -0.23286770680318772, 1.129003125269298, 2.3736668769079867, -0.33402859347349068, -0.3570002735370722, 0.85769446988954023, 0.34518757067521505, 0.87048550318454898, 0.37469487059682011, 0.10295405870647507, 1.9493493977345093, 0.11687588514731344, 1.36759237692448, 1.404733133981749, -1.3130640031244518, 1.6889752982965489, -3.0938865397936315, -0.50729714026792261, -0.3335848760887018, 0.83797909720200725, -1.3056272147314865, -0.11502035890331225, -1.1022833729851618, -1.0182164142603805, 0.31871264101707314, -0.3926882056912252, 0.46533850417431066, 0.8576547229373207, 0.57573284024343951, 1.7998831095325392, 1.8813534771269438, 1.2681062544396187, 0.94385259689886347, -0.81410606612365444, -1.0757638272737833, 1.2192023779049448, 0.40525086894394802, -0.91558618516182144, -0.44917451787992169, -1.2632990982651613, 1.0954037114817523, 0.32983039889049026, -1.542642933032556, 1.5054996619390855, -0.71119933575851602, -2.2746031410998722, 0.70689513037124607, -0.63736308093266658, 0.93323832581860233, -1.1865636767469305, -0.059637419631113416, -1.225176243613511, -1.2978076673125545, -1.3540845803980293, -0.43947437520747951, -0.38474081082467515, -0.89578066791670541, -0.0020180496863025123, -0.032525504264143829, 0.47843394877598555, -0.47401190784076996, 0.10179472707403198, -1.9290023740244433, 1.8767057852035998, 1.1831522850604692, 0.12878813764985528, 0.0031167183279362906, -1.5905565308505616, 0.53296376210704743, 0.67569908739438767, 0.39975566926291223, -0.92114408875625142, 0.69248174308857058, -0.040812673796832039, 0.55569491903776291, 2.3208502755933447, 0.64773386246839748, -0.52025451376930754, 0.94002726294752881, -0.803245689829024, -0.69753175314056659, -1.8590596805570436, -0.30231483131411591, -0.031569218142306302, 0.58727039765033318, 0.25010554335029866, 0.21445315478122598, 1.8666493100090682, -0.0055856195103243496, -0.50863896045969337, 0.51476614992353498, -0.78658411134509121, 0.18419015363295602, 0.66413736548793378, -1.2462302160142509, -1.6589583238032419, -0.93757679312269326, 0.68044759154429157, 0.81715606509227157, 0.11207415331816099, -0.92483240543181255, -0.35701340473650317, -0.57817201359247938, 0.56020550939452207, 0.13929802985275777, -0.53062387934555699, -2.9641061248086933, -0.68576900548468034, -0.95585311823049146, 2.2716267790767741, 0.30121055955566972, 0.5191988134064528, 0.65422060216099587, 0.67810180959492883, -1.3489059244305841, 0.48580650250263058, 0.69514263634524376, -1.0146739849168287, 0.040329117744860456, -1.4093636982840039, -0.31339951731169985, 0.1151165111276499, 0.41063251030305709, 1.6355840013677769, 0.43594345686407915, 0.63325332411812307, 0.22954317476674826, 1.5934836684314322, -0.93554119690002657, -1.2133434031851453, -0.34389921491856507, -0.95934651211956889, -1.3022927128771198, 1.8525935855583984, 0.47780762269419697, 0.66732023612628366, -0.19372912972418199, -0.82366637555600264, 2.6173277404710262, -0.02782784000973898, -0.56456158038811399, 1.0926764921787502, 1.7311382095833194, 0.15612456824609744, -0.025917123179898537, -0.32514073000225846, -2.1009861166246191, 0.64917132128999155, 0.24988235057663716, 1.6579803863602212, 0.61204802559883942, 0.32592734423234454, -0.68777177475241624, -0.6983352081921731, -1.5163197300030273, 0.36325304822869564, -1.0547611962717531, -0.68484582251852799, 0.58932341441607206, -2.129471907995983, -1.3132118060165945, 0.68584843710981536, -0.25810372520364633, 0.14395484518713908, -1.5400332393587313, -0.3464386249094919, -0.75477893631849569, 1.0241778198748945, -0.74024726824436848, 0.5539565162768374, -0.31505696901392449, 1.2998248582510683, 0.6981516154394134, 1.1192442619150365, 0.6838827707902394, 0.037313601960154069, 0.61646507499243586, -2.4836029521249925, -0.63242061625129409, 0.36651432166685954, 1.1851075369674919, 1.0447484120388417, 1.8198203135036533, 0.15710315260354085, 0.51353711614111286, -1.2188577280443689, 0.026061860946861561, 0.20844596803808621, 0.7595881575604565, -0.34574628536450291, -1.9692743613168182, 0.089861265988663522, 0.72654960888619036, 1.7696449185899263, -0.91880979051297818, -0.92000361954932142, 0.52330309828133081, -1.2713614835990386, 1.3341593516408035, 0.92302848268208582, 0.27562097351199621, -0.62744713885157766, 0.89291020560396184, 0.90841286371905583, -0.27533638481443512, -0.30063808997921382, -0.094376666014558325, -1.4344324799805654, 1.6261161292710871, -0.14807631994880285, -0.44239903033476924, 0.15308678571380968, 2.0370119017004509, 0.12285738244386196, -1.1607227659283559, 1.5989011814973013, 0.29544979432157459, 1.0839511327388232, -1.2218487146242645, -2.5437114885310397, 0.45297385678607349, 0.58194817461063941, 2.4150907113016573, 0.05529083154554848, 0.132753998960738, 0.92187482441421253, 1.2237351852775307, -0.28714200713821908, 1.4302618760781487, 1.0769293763938643, -2.5733818701929048, 0.80262092181844469, 0.11478130757791234, -0.34685313323554684, -0.20911587497552389, -0.90547315565267728, 0.19817745055017666, -0.74225138474674857, -0.2285197718286216, -0.10003012448697747, -0.91829653791996102, 1.7428566005007426, 0.33334383221256592, -1.100246997949522, 1.4415518371179012, 0.88218529028287651, -0.090801127735090151, -0.17074112339003006, 1.0597861138196785, -0.33210397138111003, 0.36578001459262555, 2.2688740337420432, -0.11160720864675895, 0.0062572840460555414, 0.20659996846960951, 0.91591382219964412, -0.65475528446671183, 0.20750460350020608, 1.3609097991981538, 1.7024152526219245, 0.59701946410251705, 0.47184010877596472, -1.8937356885487253, 0.71867061985655645, -0.14691528963878003, -0.15809060785353979, 1.2086819559727233, -0.46820395490245575, -0.38895659691786316, -0.30013881360117234, -1.2828451398272418, -2.0163372613579349, 0.59496702995518769, -0.60513775672893411, -0.44210764107579253, 1.1662333469449078, 0.77087991892394292, 0.31867409939356856, 1.7683014307979368, -0.11236892253588007, 1.0844592011851597, 0.16860872375694336, -0.24620292451323245, 1.4142495377914257, 1.6333932474213038, -1.0071218240556132, -0.8295088973760677, 0.18699219953190124, -0.093865771668404832, 1.6936837394029873, -1.8242656675457107, -1.8186935067660017, -0.72138241507014489, -0.99223273464581907, 1.4282186198078384, 1.361602371404339, 1.4979844825893702, -1.5486310081686023, -0.88748402322378905, -0.66101185106192928, 0.67972750668569826, -2.0750292029966033, -1.2892737109915278, 0.089233586614962307, -1.0037395660794015, -1.9158157693893745, 0.55721049371349052, -0.59587997072009136, 0.58678665317683065, -0.58744036411171829, -0.87115902507629195, -0.0056809801798265473, -0.14567345222962727, 1.2695254575552584, -0.51219829637689362, -0.60988570464772784, -1.1817693836369645, -1.7961046940409344, -1.4414216064081027, 1.9165434373943373, 0.20420271755601019, 0.43701544245929963, -1.7634911403025961, -0.30740765559305383, -1.6833803565371848, 0.56511253757838709, -0.64474983878109626, -0.74471373110519501, -0.48352085223672769, -1.3135056148110464, 0.030439762775728109, -0.055126993048741128, -0.50468334859338615, -0.47050887745346182, -0.8694281059439235, -1.5653636265335622, -0.90093645420844493, 1.5947368848073458, 0.38405934484341914, 0.41058419727011786, -0.19526393006953321, -0.25758880157006048, 0.66870845024193259, -1.7979757240472107, 0.28828648277021013, 0.20653094603155583, 0.45956954608255796, 0.9604623158329475, 0.054059978980343967, 1.3008783877207803, -0.46866642797855634, -0.063390447593833721, 0.66510476574707511, 0.35349270252882814, -0.3865615231917528, 0.051633292682168166, -0.58961293946403737, -0.72156011724399871, -0.27555679252339965, 0.98541940241009762, -2.500993739840681, 0.64503450076741342, -0.76607861952526968, -0.25609459334546603, -1.5724036741305172, 0.31032105315969216, 0.63938654655275229, -0.73626161466575324, -1.3833206957339397, -0.59514461989906298, 0.23361192057421132, 2.1763073128412085, 0.40498539772938702, 0.088683329442657333, 0.22021310846548273, 0.49986715641723362, -0.49501662216228992, -1.2284440778358676, 0.015829139875885759, -1.4184646809721162, -0.12697365741353334, 0.080982133335501541, 2.3677942888392161, -1.0133902972218027, 0.58526249944984787, -0.030060796182358459, 0.23634244853619402, -1.0354424449542972, 1.5497640105180139, 0.94211746741486424, -1.9888764767183431, -0.37578828651029017, 0.041840296512514023, 0.55549386896873598, -1.2842590882873892, 0.90099823526521094, -1.3857071926043023, -1.3819553205408786, 0.17168096275027375, 0.36105641709908953, -0.37491767433885448, 0.42388671808661188, 1.2924077740595721, 1.8211419083800544, 0.64565517665584449, 0.9415970492376261, 1.6380688845272591, 0.086452556186351337, -0.16619919663192864, -0.4322414044453648, -0.58501040240755453, -0.27952475758341438, 0.55210838765651615, -0.079829614878142163, 0.49678861330913276, 0.43252264066017398, 0.27691348872371446, 0.78033324102618462, -0.40802500006761561, 0.83960578871892855, -0.3688303687359239, 0.13751583399014969, -0.17006596817597797, 0.93990410870083518, -0.80835626441790343, 0.12775218854567996, 0.19498484709599606, 1.5729985938445161, 0.10935947351449438, 0.39891046575500316, 1.3906137421655753, 0.28077733905584312, 0.92841365729634606, -0.35976974892877678, -0.30272597738946189, -1.6794545626528765, 1.0595955237931951, -0.56393426759766985, 0.093875279213654239, -0.90103673791903527, -0.49007213753486667, 0.9751824261541161, 1.7201379517412945, -0.12549985472903044, -0.75495650789536506, -0.33662845116113288, 2.3138481092658538, -0.24716461174437354, -1.9901848198805709, 2.0842582740491129, -0.51298132751138625, 0.26636420761666413, -0.75286022797506402, -1.5194253582411921, -0.9880558168243414, 0.45298294564767927, -1.2151885865855863, 0.59074036942020236, -0.49457590524554329, -0.5608626447835805, 0.6998697687365325, 0.8846151965965009, -1.0182558341102794, -1.0156620964943912, 0.27560317411924978, -0.73518376021037568, -0.83890860144000778, -0.76290265295238235, 0.086616341720986811, -0.58889699375052462, 0.36891990545605213, -0.81210085465336335, -2.2497777689805449, 1.1023784431763448, 0.57734463023148874, 0.12860665917378025, 0.4616492543954977, -1.1791252144230071, -1.0167544477561763, 1.2295875800401017, -0.1748339805063075, -0.99731547185554836, -0.72194137926184976, -0.55468078953219913, 0.96636693969547194, -1.1055515744850106, 0.86557120159821421, 1.9001938118277415, 0.34490180583275082, 0.60149515062356085, -0.17198090800482524, -0.58581077282953253, -1.0132177011050578, -0.82517053289916953, 2.1097322201396564, -1.7833494885710572, -0.60864664944103175, -0.50286647229976689, 0.047089461388598465, 0.29540591762255952, -0.35087731376336545, -0.64929308862745605, -0.068478360971755373, 0.093066726451454071, 1.1653093013646216, 0.88903741247802126, 0.18467433192943294, -0.31815146387362508, 0.94005858608370407, -0.49651154878390763, -1.4457376118186249, -0.025253744570856364, -1.3511373294643372, -0.58930255500851358, 0.64739770978377642, -1.413737905136218, -1.0274123594806588, -0.73669813110691984, 0.73586440676735021, -1.0234314324530731, 1.3684066831023429, -0.4388038070346455, -0.95976869002381726, -0.1944600749584012, -0.56491983227749587, -0.75859554580102628, 0.5428671601749111, 0.18572864595741936, -0.54591554445139789, 0.79531259167473622, 1.2184561827823546, -0.06858600529136169, -1.5108253637114588, 0.31259848153535985, -0.14050079468328339, 1.7019653128962999, -0.94114207023657537, -0.3035837083537779, -0.83857622519941499, 1.3942371412703605, -0.0086043500169225278, -0.9922066450784216, -1.4083387960563243, -0.38289633453060673, 0.8756115675917715, 0.066438650665529939, 0.71520552771806667, 0.31686640212776873, 2.0817749551226483, -0.22842105371014909, 0.46811684132744752, -1.4303738093484344, 0.83389676013536929, -1.2981437924035137, -0.40984584599246965, 0.69463533932601218, 0.87434667339178196, -1.1030551985525401, 1.4927115705957852, 0.45112346549373444, -1.751683634928177, -1.3155479183063712, -0.29860200081081001, -0.38325317053770641, -0.74736728437713285, 1.0248741114738629, -0.12912069469063919, 1.1453476034933809, -0.73997252897110688, -0.69818569637762007, 0.17577952422715651, -1.8017266281762103, -0.64911649372928737, -0.86087690305170983, -1.8208832689657348, 1.4791365936973782, -0.15321751009965154, -0.2566703912507976, -0.78904455398865492, -1.4256305321200577, -1.5343441377685103, -0.22758395416474508, -0.95650392551661523, 0.63339730233028146, -1.7776128574204957, -1.1905107585799568, 0.13325527112194446, 0.95739207656574055, 0.76952540035423245, -0.86657937399755558, 0.82088969945335399, 0.31741786756926571, -0.71490562109669731, -1.3453754327580103, -0.74676179451701019, -1.4148970384403294, -0.94065115025353918, -0.34614528798956046, -0.19955872170645214, -0.33503121333277874, -0.29405661461167915, -1.226693603828928, 0.71442350097630003, -0.99579739822922397, 0.54019934722245888, -0.2632215300281408, -1.2877319871494957, -0.64032841437537713, -0.18871356420942426, -0.163821080646084, -0.15926926018243101, 1.4522300736091172, -1.1052160890702467, 0.4939084401373835, 2.2005969850692901, 0.22759256749795398, 0.053210643435737739, 0.38153326629477019, -1.7944943319467448, 1.3719879247482256, -0.68265503491434865, 0.99359373939823958, -0.36476063644388307, 2.1085971403538819, 0.096877718182282885, -1.1303146625864078, -1.4861852425395443, 1.8217407494995888, -0.79620976011812428, -0.0070500338810168097, -1.4186932218552446, -0.86309671638423946, 1.6095117589534027, 0.022094942318574805, -0.37177483135939382, 0.28706506388178782, 0.095284782021094874, 0.4568066116575194, 0.60050257301607257, -0.86865718761261035, -0.27064275220918133, -0.8243904474862308, -0.30932320572069238, -0.89576282662130846, -0.67479417499228778, 0.9640334449529151, -1.9511213868318338, -0.89536595709890476, 0.35134004285095038, 0.50334067740577404, 0.28236760390267779, 0.90122802451526907, -0.1037696767064728, 0.061656035584830814, 1.2443252967886398, 0.13709552022709603, -0.10149699750970524, -0.4576709468811252, -0.88870262431463631, -1.6172483293700413, 1.0767870027891935, -0.66105924398727578, -0.68752236002704603, 0.61061466493412342, 1.6497532013153846, 0.39528656708902377, 0.31626839343630858, 0.91405079254011778, 0.077446425958859741, 0.1974195188373071, 0.71822202442126959, -0.7117247765627821, -0.97022293175446872, -0.54249625932454204, 0.29228097257364016, -0.71821337778505967, -0.34992800318370504, 0.64128753504653524, 1.0402187377923902, -0.91920812699051924, -0.52324203708466843, 0.20168614621154932, -0.26451031198645519, 1.0035255363957547, 2.2192493998830076, 0.044462996062754882, 1.2111886220031969, -1.7184335933222599, -0.4732357315380859, -0.386383129788128, -1.0114362701944135, 0.99753661922784143, 0.49540062179037364, 1.4205226550295382, 0.39064035053287, 1.5304628720856337, 0.89544466587964344, 0.1365434660592196, -1.2453161776213737, 0.24302682144825832, 0.78082197037741408, -0.51858636620557774, 1.7980620372874128, 0.39640210578438106, -0.00098708246535709056, -1.1191406213438697, -1.0925089142271045, -1.5230682533966868, -1.2044245297582867, 0.63127198544905305, -2.1928813251775745, 0.86863446798090238, 0.25467609561428711, -0.14607612155452518, 0.37772770500871028, -0.66202332301553213, 1.7702256334793698, -0.38733521977878921, 1.8890288566774591, -1.7557379422403729, -2.0404025274566071, 0.20481304420717603, 0.50806827846657265, 0.4117301121204528, 0.87435288881144069, -1.3608829844238435, 1.3937166187057852, -0.25699536108046972, -0.079153205188857517, -0.95564367558463925, -0.60555004908165078, 1.3738037873788136, 0.8740789365246785, 0.24477713375394947, -1.0631942131290184, -1.4566853309231349, 2.3955405135747787, 0.34464411114257237, -1.8066929029531111, -1.2207815376277478, -1.1878572670527048, 0.61315909601677376, 0.46980644352804568, 1.1960322166365491, -0.69187247480135883, -0.22818821837394246, 0.34919596595967567, 1.2604111188969065, 0.42154808668035021, -0.47912828497487908, 0.7631293646399272, 0.29297485947941493, 2.8377431311091361, 0.69328711739284554, -0.84019326796167826, 0.031614259780960385, 1.6457567170868077, -0.85591378319723099, -1.1355776878310386, -0.16633067139640428, 0.29279645590907405, -1.6293115878689315, 1.3020035061178137, 0.39585142326003864, 1.8668665323053109, 0.071624252939670438, -1.1508897801145481, 1.9687514740444976, 2.3264078186388755, -0.44243888965591655, -0.84231772791242754, 0.64902778695914798, -1.6682255656244229, -0.1944717542919206, -0.67907970025892728, 0.25016774970692351, -0.70361244316242799, -0.35685052506494902, 0.93281385756252466, 0.11341681715457591, -0.020543895201840408, 0.62862219576715583, 0.14446278589493952, 0.62310959958393508, 0.99765838419101538, 0.53482554645516178, 0.46366502238324458, 0.11245722572738341, -0.10990578827026824, 0.36122021391241321, -0.72224165386576256, -0.49958225548852336, 0.7973907226905087, 1.0429499208107813, -0.60437680705513852, 0.35353780804142937, 1.3237173165055371, -1.1626039191274558, -0.42481126385779339, 2.0234802312266389, 0.41360961074711872, 0.33536494280073165, -0.45587540097876644, 2.5794151132294618, 0.86600436392501279, 1.4273666699490932, 2.9629405476622956, 0.64401961117098483, 1.220009720860755, -0.60991277716246972, 2.0136887860971688, 0.78438249622524192, -1.8259213760563748, 0.22098604872022778, 0.30352188611998832, -0.0018529545886022826, -1.6292468618334972, -0.84273568055349279, 1.3571564526750952, -2.2770341382766097, 0.3063891183865553, 1.5208107283614389, -1.2925037436975457, 1.0824878257554256, 0.016125304732676003, 2.0989799622723235, 1.7413396709657307, 1.3323580390359295, 0.41263268778414475, 0.42385596952741372, -1.4461624691589181, 1.3877570731624804, 0.82609929206253485, -2.2602061994384992, 0.6282987579703293, -0.64376668398663306, 0.25084421220305414, -1.5362894661072726, -1.014378642100372, -1.3610402796061196, 0.4067888549274668, -0.34098579791911621, -0.065380152326002, -1.9441333119742106, -0.19746811505648784, -0.94102219955626154, 0.45517006592000292, -0.94536578032308816, 0.55756422108202164, -2.7921689010535347, 0.39818772675708453, -0.7699950052341904, -0.39133521073958866, 1.4145251432219561, 0.39301387473923488, 0.40091528063997223, -0.93702998646026869, 0.18036884330813788, 0.62681817067239454, -0.16272069227129224, 0.37729347040681488, -0.63196707961384579, -0.23700420021769875, -0.023469728614139398, -1.1149215003103263, -0.031800533512766307, 0.40604386237014239, 1.3751200559939467, -0.026618504981336655, -0.28668995017043364, -1.1624173263438067, 1.480091521990659, -0.55653966003104782, -1.3596984988407503, -0.51372591270797063, -0.26859398510422283, 2.0924357101740974, 2.623911504406415, 0.39660548054743083, 1.296614360649317, -0.96872325371814871, -1.0875772880457188, -1.392846289122446, 1.3429331466028969, 0.5305174807364047, -1.906680135411482, 1.4423921070947836, 0.60502395176857482, 0.48972498359790528, -0.71971034444855952, -0.54485034723097003, -0.35090654773745616, 1.7899764259323623, 0.37337140424445986, 0.27113206574241194, 0.76535470309835918, 0.21362074003369794, 0.23710779388006978, 1.5577714719588702, 0.60049390856713059, 1.1738709197267883, 0.8690322952923758, 0.63679986517443776, 0.49915590953684624, 0.89831029782445082, 0.76149886935421551, 0.59474043522679998, -0.12071990800048225, -0.42445070031406257, -0.017861804442843559, -0.80122992472104759, -1.3976542761433988, -1.5733653370505163, 0.52281116648657799, 0.28029499112008077, -1.2431768216766235, -1.7482322939561459, 0.13381512948083349, -0.49204708418565896, -0.27003352373944411, -1.7196570063550249, -2.132888557911075, -1.8749441246128591, -0.71066121401545124, -0.94237644267057619, 0.76660012494609187, -1.248090226738412, -0.81137855832168537, -1.1870853602042279, -0.60145959190563059, -0.044809174679081215, 0.52363703269086148, -0.79456171323119051, 0.046520975264673671, 1.1807284548484664, 0.57342594025801308, 1.2853402537753185, -1.5725182398375788, 0.38324482693641465, 0.67595711989558327, -0.14108565146941748, -0.25252596942987005, 0.10527711286406329, -0.85645254282494454, -0.32841863412681993, 0.81603725308325692, -0.32787754879912945, 0.97152372510511709, -0.61515181295141574, -0.15838941084269983, -0.68109756725951054, 0.69777269589532109, -0.051453701576314181, 0.15015089033774651, 1.7100894507666522, -0.070880270289390923, 0.052214496430427228, -0.91327211372917427, 0.37152611744979375, 1.5797683319295797, -0.60281439149715865, 0.81269612842780981, -1.3093060661300309, 2.4827939602251288, 0.99046260193410995, 0.65221545127052138, -0.46565077719655185, -0.81238016651602207, 1.9246961828609657, -1.3384222411441251, 0.90980117301214813, -1.046708070167949, 0.91793172600443329, 0.48669362533282823, 1.1201651534267667, -1.0431768588039212, -1.3001858750312294, -0.51345407746693505, 0.87643468851571349, 2.2992901475276746, 0.14123562824031752, -0.14983082466481817, 1.1913792721225482, 0.89606213408244906, -1.1847323370756666, 0.32658897048806013, -1.8313142834409415, -0.86756331016641197, 1.0543856749090934, 0.99724839694555534, 0.035979430990901617, -0.91306722057828793, 1.1954080088518242, -0.75781379554374939, 1.4554041159297724, 0.091646399848139784, 0.39405690791665637, 0.39637367824952124, 0.20785773643625624, -0.090404307247370821, 0.44837164628311199, -0.83936721744696841, 2.0082523673835713, -0.30706523593615415, -0.15714352226691902, -0.32032794166128598, -0.37363647220447005, -0.89301592939203023, 0.49245085104320602, 1.4328784236909295, 0.99286654234387461, 0.50927022813638279, -0.34142436151807343, 1.3473356742494031, 0.32710987099767092, -0.65999396241490316, 0.48047786496811296, 0.16830837980713079, 2.7601788702916901, 1.6596012152554314, -0.53083451695925021, -0.69474325682381222, 1.0927040984399909, -0.24068566550259143, 1.3829285669612288, -0.79257529207863486, -0.24294258171701286, -0.1784870934421259, 0.29241743831617562, -0.22156159900659894, 0.35488112593990123, 0.81616706343119849, 0.29588931131084495, 0.27314875737400829, -0.1698512804196799, 1.4350835420321919, 0.44556379281605452, -1.9987861927233499, -0.11034182879587706, -2.6577755590312018, -0.7229817446587149, -0.44601484415924725, -1.4554219695062831, 1.2581532919437615, 1.094627099365894, -0.017323130417878144, 1.1308824946523803, 0.49959706757439931, -0.51385475215501641, 0.36135018887592812, 0.46189808323556442, -0.25718665717277078, 1.0439029372437298, -0.40328395920650328, -0.5587870178650125, 0.087960843078009554, 0.39514740480863297, 0.085592388464315036, 0.51661165746257587, 0.028724001801531198, -0.012592552783843584, 0.67955963798910612, -2.1239105662090858, -0.73378292666265432, 0.3060198167558662, -2.3482410869332346, -1.127874479263886, 0.48151328775895325, 0.48636690469536931, -0.38504682154318254, 0.38795659926119186, -2.102823559609917, 0.30850858416941429, -0.17483531331362431, -1.2316502118972545, 1.846387210147761, 1.3667191225505519, 1.5285482638980807, -0.09173326195955589, -1.1656074198928636, -0.45722295102333155, -0.70668636735413881, 0.95750496142092145, -0.35330741999803017, 0.78085048007915259, 0.64420590600816696, -1.7510280294438731, 0.48652307775304326, 0.35314676249960059, 1.6570068873457471, 1.6012582551765373, 0.1205562561437913, -0.14978984107558374, -1.2087533834704043, 0.27454757366236043, 1.5472323183245331, -1.059322818823708, -1.4613534340368408, 0.72439381953307613, -0.19255715771446821, 0.71713079445248362, -1.2369107242495501, -2.881379185185224, 2.5632572894925194, -0.45389743473971417, 1.1107377420807238, -1.0622647352857537, 1.635030435209299, -0.4677657939775669, 1.4084987998439233, -0.0091732783991610081, 0.48979858738694199, -0.06056524261249116, -1.5181026600415235, 0.87207281001680659, 1.6696263130829032, 1.5471187336510914, 0.17342987010722549, 1.2332548580653371, 1.4059635701808708, 0.58581281518959727, -0.66857385144080472, -1.487022916012769, -0.83978303867020521, -1.252733577913107, -0.76280501202980788, 0.95040612247965606, 0.20885744512389515, -0.13943424002210986, -1.3843631333332147, -1.0178356000803774, -0.99683293854552113, -0.36955725875571704, 0.91815657345436308, 0.95880960811113569, 1.9597171542573792, -0.62603608114474385, -0.79603412306511945, 1.0445275917963108, 1.017561136699346, -1.3998465734641894, -0.57499743006898185, -0.059613197371932235, 1.6950040743466721, 0.32595457157922825, 1.0939367848074206, 0.49799044098736173, 0.81396545254283392, -0.33514469310797962, -0.19215604964735325, 1.0056269680956476, -0.10445524403573932, -0.90466969931090324, -0.22221789221349972, -0.5025634548406126, -0.2149504576684359, -0.3293144449386271, -0.35737547707439504, -1.0989112623639534, -0.23688677643431807, 0.41622568603141058, 0.25724204487136587, -0.30400422971370905, 1.712029666998689, -0.55896628719991903, 1.6032749589261868, 0.26440820282972993, -0.36904157132778048, -1.2890423957114683, -0.35536207257393443, 0.4731980620480577, -0.55776046671806523, 1.5484335290898337, 1.3109237231680051, 1.1490048420144914, -0.064131566607289234, -0.60312551741095133, 0.98560418949273076, -0.1948264070093369, 0.49507593647605758, -0.33122141004606293, -0.19414649848954896, 0.046536850046234819, -1.388514566173638, 0.5645999188979367, 0.36775340623684233, -0.68894809998582496, -0.40110853117296108, 1.2698471971527263, 0.080060059074555892, 1.456293347377831, 1.5154358967696486, 1.256535106126474, 0.22224826032623274, 0.42231521207865158, -1.368318287650891, 0.64068577743518462, -0.64639199209546883, -0.0082081407437137963, 0.78805652064797804, 1.35122903221644, -0.40347109638651651, -0.50943756967224807, 1.1117699620768804, 0.83897555072634955, -0.55308259886111644, 1.1985488720703268, -0.16068591840645366, -0.29368596921632562, -0.21106075684324899, 0.16313949931833976, 0.72285654735440086, 0.088014366783531237, -0.60248060378979207, 2.0190555325478994, 0.39214883905239889, -1.3742429896469754, 1.0051412100265327, 0.79054173935176186, -0.17353199072406195, -2.1713717031553879, 0.74950022100235991, -0.83261090766872647, 1.2150221673073218, -0.25957139684459385, -0.1813450275343042, -0.94172725485728792, -0.095987077287423048, -0.042540442758983159, -0.81390951831344771, 1.0099312721112692, -0.62490924469738374, -0.88871906757559671, 0.31257072447346063, 0.55618707705493875, -0.93889784222152473, 0.049681960726926273, -0.73931088267236178, -0.7119956678681415, 0.37326610313916353, 0.49017557428423153, 0.50568358958831627, 0.8681172003106129, -0.36916877341115023, 0.35141034700375667, -0.7947384417906046, 0.57236782724468505, 0.85690330169025974, -0.47256301240280446, 1.0118875965479386, -0.63960998421163651, -0.47798553038303793, 0.14463720764690177, -2.321819815010802, 1.3263615905305262, -1.2332123452664943, -0.91779527778010139, -1.3463293268783516, 0.098731286520251857, 1.3067906371779197, -0.17715209157699913, -0.57605381333781125, -0.32169750954049409, -1.295570010878776, 0.65439491496886648, 0.70459176356626263, -0.92344795409091129, -0.77994626703344605, -0.66174060793051304, -0.059344557391063139, 1.4654269340474069, 1.458227137600338, 0.71439875571942046, -1.0663600457404427, 0.43428793785678321, 1.9141133002870123, -0.042177820312274961, -0.66917015359552035, 1.1131704424960487, -0.45844258522936265, -0.83092638192015511, 1.0491820287939198, 0.63039566301394268, 0.14737676717219197, -0.22011108207396951, 1.0750476133651816, -1.4919081310010938, -0.21949959582694434, 0.19140099923321865, 0.19550187413928086, 0.49939665048271636, 0.64537226379087831, -0.25192585094237518, 0.80314735451234609, -1.0068042185610304, 0.073010415041282459, 1.5529102631015281, 1.4330652363123191, 0.0029397788383722849, -0.34736028284548504, 0.082788220348791339, -0.61889542801934661, 0.5585880111701812, 1.9923818297688358, 0.32704078244209339, 0.88438134964757564, -0.42147216458970999, -0.71130545777584842, -0.67161702907444853, 0.33292575909585143, 2.4359560232515225, -0.36832463061552373, 0.47358774286845051, -0.62069661184398228, 0.70270578150989138, -1.077498456877769, -0.67360393671372543, 0.66841806543763549, 0.51584500762942265, -1.1871869094956913, 0.25434901887756423, 1.7438706922635925, 1.2939939128130802, -0.18789346844893901, -0.14524581449934929, 2.3934975813014812, -0.69266623815256945, -1.7323203420742073, 0.20298758851464294, 1.1570470238953205, -0.68727554353933706, 0.79421754426173752, -0.50531496386978791, -1.616181742631287, -0.82316237514359369, 0.60069926292664022, 0.65616536460564534, -0.42371336172816743, 0.18458090742111263, 0.36975744748278566, 0.11772269610717438, 0.76870793066294252, 0.7720120270541464, 0.75653895898031243, 1.3455639867454863, -1.8403959631767588, 1.0617106905708655, -0.76974122977873216, 0.051677187415605348, -2.1662257463766688, -0.013119744846694781, 0.59457312947890728, -1.2458545105775727, -0.071601961993845928, 0.74131534699974744, -0.3393062932672149, 0.065947039665276888, 1.2842667965593999, 0.034296516416804694, -1.4461471899312084, 1.4868662868507905, 0.14789919747150923, -0.78870097523041471, 0.6533682016145177, 1.4534322491752298, 0.83848201015920398, 0.29035983421113692, 0.80681597537814076, 0.91107874395544408, 0.49938555772072279, -0.66062885235968927, -0.20378315743343509, 1.3416980141957799, -0.69552162793351047, 0.088931430758100324, 0.14812211525147881, -0.32748184822367393, -0.10629265289668503, 0.069998726204287084, -1.2400104569389727, 0.76235165596491938, -0.34094513728872022, 0.032217015381188735, -1.3646544066223403, -0.50509974757563636, 0.97213614599453824, -1.7630726762647864, -1.1933397925016413, 0.53750231846076435, -0.31199878066537146, -0.088991809576926192, -1.5574168511026707, 1.7810439791571384, 0.19745323513820626, -0.73213826464249165, 0.17065968801934681, 0.77967047777988585, -0.51115274274461986, 0.42534657461532249, 0.34034280893034191, -0.56217520503337248, 1.6616847337069829, 1.5475919869883479, 0.034446766344215701, -0.23141275591301635, 1.0822606848232577, -0.12190544623287239, 0.52000847187532762, 0.90310950908767429, -0.33895287445134314, -0.27506375061469623, 0.40059019092634479, 0.40623977085820345, -0.46104139722766174, -0.41272117197429881, -0.39966469629118484, 2.6872270049939568, 0.7460444348349593, 0.32757465238438072, -0.013991186032114541, -1.0751965821119769, -1.3181896168309051, 2.1881835212445417, -0.38860598183432221, 0.7995989219066012, 1.1803281036307605, -0.69312746258825908, -1.3193815204021688, -0.00048680184674413811, 0.65195354530614003, -0.70161940880844609, -0.33931554843453093, -2.1270231238934327, 0.21461207480158007, -0.43952998636741281, -0.36284177491552444, -0.2980633778624166, 0.23310036591467481, -1.4758867968617819, -0.98462171750940786, -0.17381912159161128, -0.41714844014744018, -1.1134093729655805, -0.61815218968470342, 2.0501225204320859, 0.040740977106945069, 0.78314893323253076, -0.22866359753664073, 0.95036756308375803, -0.50270809661045113, -1.6720855325134376, 0.22837088965736332, 0.93648856753862764, 0.20571187441566605, -1.8300800698361683, 0.64848979813447361, -0.8412796851667752, -0.073190231459127703, -0.75050472096813658, -1.4165964642576461, -1.155781224067403, -0.61101274921436943, -0.32896552560269704, -1.2980073392186557, 0.71772259046668874, -1.3850591002562969, -2.5656446386558205, -0.24559943107052695, -0.2481294154705731, -0.22617321012851013, 2.4815472998414707, 0.99523931344405059, -0.57227081971948768, 0.60481284102177191, -0.53797625269529226, -0.65191093576131398, 0.2377675430082116, -0.96065826798021881, -0.46189946653250324, -0.31419229326622616, -0.55202270721009294, 1.9762790373253649, -0.17221424914151379, 0.27305706278396996, -1.0363850749044454, -0.55619683267677655, -0.59838846637904974, -0.40208178013361612, 0.16701187600372205, -1.2432336433038254, -0.5076947058455118, 0.93227489243608741, 0.21828256650951772, 0.17445186490160075, -0.20966481324602923, -0.024084398746782559, -0.61469173932692722, 0.47265078007232386, 0.54856656432527306, -0.34620576050858687, -1.0467697545506431, -0.51871651598766733, 1.1799071193289736, -1.7804914259238038, -0.17592193512655571, -0.15341103536061196, -1.4086918084845714, -0.66057927120906446, 0.32310439967027704, -0.22378422231310033, 0.71162602379444162, 0.096638230480943235, 0.95772511545667927, 0.3841196617260329, 0.50655438726641189, 0.07684522382234367, 1.7458999674043862, -0.81573378800438612, 0.32853665671418664, -1.0380915406688211, 1.2364564262554028, 0.20043717038157852, 0.46622931720536925, 1.1896197279978309, 2.1989701129450072, -0.9893035021473856, -1.2853514839004281, -0.11636257902354792, 0.028634808233156082, 1.7203987994667322, -0.27018788695450502, -2.0467135661153031, 1.8154833985315788, 0.49422258832620436, -0.017258412075499621, 1.6264755276879312, 0.66840487028918627, 0.3493318511460225, 0.47142383954168526, 0.080227050326743862, -0.73612048180878986, 1.0867624311841857, 1.6195664129893204, -0.45441410191434001, -0.63533080302866785]</Parameters>
			</FullConnection>
			<FullConnection class="pybrain.structure.connections.full.FullConnection" name="FullConnection-52">
				<inmod val="hidden0"/>
				<outmod val="out"/>
				<Parameters>[0.34878600165647772, 0.067841290806442134, 0.46965200508385857, -1.0958507799652935, 0.7519846848551236, -0.90350622513220191, -0.11631379795794494, -0.53363254816918093, -0.69020919654715718, 1.490993427010936, 0.25497909271853503, -0.18322870140566838, -0.043271039502621983, 0.67518390665982819, 1.1556262193751565, 0.96032676632149183, -1.2346749471935801, -1.0465254581020498, 0.88426413597213149, -0.28997294878722135, 0.07955555784372649, -0.81013591909521954, -0.55664106556977555, 0.64129288239566362, 0.26497730884577769, 1.0333711561825485, 0.11327973473844606, -0.18174431248942438, 0.28849845233832122, 0.19217564385100541, -1.4854651330436892, 0.42548812393440855, 0.93572887365030355, 0.50363428837975488, -0.70557004887965935, -1.9313064103421638, 0.098958508396730802, 0.7735350853520333, 0.50105937254592492, 0.15355389964505645, -1.0060199215403096, -1.3991719000966227, 0.034796817281926858, 0.96217219249785324, 1.6326648277137137, 0.31503589394286297, -0.14162189923256205, -0.28488987558819051, -0.40991961800303856, 0.55656364889570842, 0.72271495749380277, 0.80105905994621596, -0.46069847238523937, 0.012818996345681793, 0.095211811147182898, -0.60944713105198522, 0.25106303098253757, -0.53154838425705497, 1.1797089925475148, -1.4164000462085229, -0.48490619443780364, -0.34611176650981068, 1.4317697000515162, 0.77616732845605629, 0.25999977063230695, 0.4406300821562309, -0.89459683755888275, -2.2011713179102199, -1.0623537888477397, 0.44781852960763596, 0.68302501655525705, 1.1263977026196579, -1.7398809010454395, -0.3664807365686652, 2.6520324411788607, 1.5116208238472135, -1.4710022422959366, -0.40246848020174203, 0.53703704302703126, -0.4427922267562624, 0.60927603809468556, -2.8235211147722712, 0.71787265228398567, -1.1071844412726024, 0.094234277094877514, 1.7116993786034287, -0.203686642984482, 0.82993493860082812, 0.2339989065722978, 0.30961536071855972, -0.97624306801873584, 1.1189265459799314, 1.4235036190825521, 0.14163811955462363, 0.667183353833666, 1.6714674940114389, 1.2242454385568913, 0.84048760436081138, 1.5093213309484872, 0.093600997474028585]</Parameters>
			</FullConnection>
		</Connections>
	</Network>
</PyBrain>
